LICENSE
README.md
pyproject.toml
src/__init__.py
src/cli.py
src/file_iterator.py
src/image.py
src/image_manipulator.py
src/main.py
rexize-0.2.3.dist-info/LICENSE
rexize-0.2.3.dist-info/METADATA
rexize-0.2.3.dist-info/WHEEL
rexize-0.2.3.dist-info/entry_points.txt
rexize-0.2.3.dist-info/RECORD
