Metadata-Version: 2.1
Name: rexize
Version: 0.2.3
Summary: CLI to bulk resize and convert images recursively
Home-page: https://github.com/joelee/rexize
License: MIT
Keywords: cli,image,resize,convert,bulk
Author: Joseph Lee
Author-email: joel@joeworks.com
Requires-Python: >=3.11,<4.0
Classifier: Development Status :: 4 - Beta
Classifier: Environment :: Console
Classifier: Intended Audience :: Developers
Classifier: Intended Audience :: End Users/Desktop
Classifier: License :: OSI Approved :: MIT License
Classifier: Operating System :: OS Independent
Classifier: Programming Language :: Python :: 3
Classifier: Programming Language :: Python :: 3.11
Classifier: Programming Language :: Python :: 3.12
Classifier: Topic :: Multimedia :: Graphics
Requires-Dist: icecream (>=2.1.3,<3.0.0)
Requires-Dist: pillow (>=10.2.0,<11.0.0)
Project-URL: Repository, https://github.com/joelee/rexize
